{
  "npCommunicationId": "NPWR47300_00",
  "title": "Halloween Memory Quest",
  "platform": "PS4",
  "trophySetVersion": "01.00",
  "hasTrophyGroups": false,
  "totalItemCount": 22,
  "trophies": [
    {
      "trophyId": 0,
      "trophyHidden": false,
      "trophyType": "platinum",
      "trophyName": "Halloween Night",
      "trophyDetail": "Unlock all trophies.",
      "trophyIconUrl": "https://image.api.playstation.com/trophy/np/NPWR47300_00_00BC35175A41D3072912B0CBEB2EE41ABBEE041890/9D177C44DF47FF34F0F1F2AA2F410FBF78E52C2D.PNG",
      "trophyGroupId": "default"
    },
    {
      "trophyId": 1,
      "trophyHidden": false,
      "trophyType": "silver",
      "trophyName": "Easy Mode",
      "trophyDetail": "Successfully complete easy mode.",
      "trophyIconUrl": "https://image.api.playstation.com/trophy/np/NPWR47300_00_00BC35175A41D3072912B0CBEB2EE41ABBEE041890/18D71D76E1A5FCD3E2DCC5613EEE84ECF33D0434.PNG",
      "trophyGroupId": "default"
    },
    {
      "trophyId": 2,
      "trophyHidden": false,
      "trophyType": "gold",
      "trophyName": "Medium Mode",
      "trophyDetail": "Successfully complete medium mode.",
      "trophyIconUrl": "https://image.api.playstation.com/trophy/np/NPWR47300_00_00BC35175A41D3072912B0CBEB2EE41ABBEE041890/6B6B8E1C45993FBACBA8D5FC91D817C11200AF6F.PNG",
      "trophyGroupId": "default"
    },
    {
      "trophyId": 3,
      "trophyHidden": false,
      "trophyType": "gold",
      "trophyName": "Hard Mode",
      "trophyDetail": "Successfully complete hard mode.",
      "trophyIconUrl": "https://image.api.playstation.com/trophy/np/NPWR47300_00_00BC35175A41D3072912B0CBEB2EE41ABBEE041890/8E1F62920CF5F32BFEFD1BA27516220509834EEE.PNG",
      "trophyGroupId": "default"
    },
    {
      "trophyId": 4,
      "trophyHidden": false,
      "trophyType": "bronze",
      "trophyName": "Mummy",
      "trophyDetail": "Find the Mummy",
      "trophyIconUrl": "https://image.api.playstation.com/trophy/np/NPWR47300_00_00BC35175A41D3072912B0CBEB2EE41ABBEE041890/AF29099E21B0892AAC2D8D3DBAAC40F5B5F05081.PNG",
      "trophyGroupId": "default"
    },
    {
      "trophyId": 5,
      "trophyHidden": false,
      "trophyType": "bronze",
      "trophyName": "Ghost",
      "trophyDetail": "Find the Ghost",
      "trophyIconUrl": "https://image.api.playstation.com/trophy/np/NPWR47300_00_00BC35175A41D3072912B0CBEB2EE41ABBEE041890/BE7EA91A62EB5775850A2C40450DCB3FC81719FB.PNG",
      "trophyGroupId": "default"
    },
    {
      "trophyId": 6,
      "trophyHidden": false,
      "trophyType": "bronze",
      "trophyName": "Magical House",
      "trophyDetail": "Find the Magical House",
      "trophyIconUrl": "https://image.api.playstation.com/trophy/np/NPWR47300_00_00BC35175A41D3072912B0CBEB2EE41ABBEE041890/7033F16FDE5D933AE09CA002F41B1B7A537D82DD.PNG",
      "trophyGroupId": "default"
    },
    {
      "trophyId": 7,
      "trophyHidden": false,
      "trophyType": "bronze",
      "trophyName": "Pumpkin",
      "trophyDetail": "Find the Pumpkin",
      "trophyIconUrl": "https://image.api.playstation.com/trophy/np/NPWR47300_00_00BC35175A41D3072912B0CBEB2EE41ABBEE041890/24FEAB15E66C314C3060474E9D30727EBCD0EEE8.PNG",
      "trophyGroupId": "default"
    },
    {
      "trophyId": 8,
      "trophyHidden": false,
      "trophyType": "bronze",
      "trophyName": "Zombie",
      "trophyDetail": "Find the Zombie",
      "trophyIconUrl": "https://image.api.playstation.com/trophy/np/NPWR47300_00_00BC35175A41D3072912B0CBEB2EE41ABBEE041890/0E58E42CB1BC32E675B96F5469D69A2759788433.PNG",
      "trophyGroupId": "default"
    },
    {
      "trophyId": 9,
      "trophyHidden": false,
      "trophyType": "bronze",
      "trophyName": "Bat",
      "trophyDetail": "Find the Bat",
      "trophyIconUrl": "https://image.api.playstation.com/trophy/np/NPWR47300_00_00BC35175A41D3072912B0CBEB2EE41ABBEE041890/799ACB38DBC46FD9466536093C88E382AF8F9E4E.PNG",
      "trophyGroupId": "default"
    },
    {
      "trophyId": 10,
      "trophyHidden": false,
      "trophyType": "bronze",
      "trophyName": "Owl",
      "trophyDetail": "Find the Owl",
      "trophyIconUrl": "https://image.api.playstation.com/trophy/np/NPWR47300_00_00BC35175A41D3072912B0CBEB2EE41ABBEE041890/180A0F10D580558ED39ADF6DEBABD93E0DE42BBE.PNG",
      "trophyGroupId": "default"
    },
    {
      "trophyId": 11,
      "trophyHidden": false,
      "trophyType": "bronze",
      "trophyName": "Dracula",
      "trophyDetail": "Find the Dracula",
      "trophyIconUrl": "https://image.api.playstation.com/trophy/np/NPWR47300_00_00BC35175A41D3072912B0CBEB2EE41ABBEE041890/48B49B1A9B815BBE9C6220136881BEDE3CD0C0AC.PNG",
      "trophyGroupId": "default"
    },
    {
      "trophyId": 12,
      "trophyHidden": false,
      "trophyType": "silver",
      "trophyName": "Witch's Cauldron",
      "trophyDetail": "Find the Witch's Cauldron",
      "trophyIconUrl": "https://image.api.playstation.com/trophy/np/NPWR47300_00_00BC35175A41D3072912B0CBEB2EE41ABBEE041890/23906AB0D08D81F05E48F9033A196D16FD40FABF.PNG",
      "trophyGroupId": "default"
    },
    {
      "trophyId": 13,
      "trophyHidden": false,
      "trophyType": "silver",
      "trophyName": "Candy",
      "trophyDetail": "Find the Candy",
      "trophyIconUrl": "https://image.api.playstation.com/trophy/np/NPWR47300_00_00BC35175A41D3072912B0CBEB2EE41ABBEE041890/0BDF2123DF981D2D3F56CE7298C7A33EFD2D6A09.PNG",
      "trophyGroupId": "default"
    },
    {
      "trophyId": 14,
      "trophyHidden": false,
      "trophyType": "silver",
      "trophyName": "Skeleton",
      "trophyDetail": "Find the Skeleton",
      "trophyIconUrl": "https://image.api.playstation.com/trophy/np/NPWR47300_00_00BC35175A41D3072912B0CBEB2EE41ABBEE041890/65CA21BEB0776BF6A885BF4A8972844DC547253D.PNG",
      "trophyGroupId": "default"
    },
    {
      "trophyId": 15,
      "trophyHidden": false,
      "trophyType": "gold",
      "trophyName": "Cat",
      "trophyDetail": "Find the Cat",
      "trophyIconUrl": "https://image.api.playstation.com/trophy/np/NPWR47300_00_00BC35175A41D3072912B0CBEB2EE41ABBEE041890/B65FAC1D83432E749F81A9C08C55FAB7E4CF6375.PNG",
      "trophyGroupId": "default"
    },
    {
      "trophyId": 16,
      "trophyHidden": false,
      "trophyType": "gold",
      "trophyName": "Clown",
      "trophyDetail": "Find the Clown",
      "trophyIconUrl": "https://image.api.playstation.com/trophy/np/NPWR47300_00_00BC35175A41D3072912B0CBEB2EE41ABBEE041890/656CF2523050A69D69BCB00FED6F744982B6A9C3.PNG",
      "trophyGroupId": "default"
    },
    {
      "trophyId": 17,
      "trophyHidden": false,
      "trophyType": "gold",
      "trophyName": "Voodoo Doll",
      "trophyDetail": "Find the Voodoo Doll",
      "trophyIconUrl": "https://image.api.playstation.com/trophy/np/NPWR47300_00_00BC35175A41D3072912B0CBEB2EE41ABBEE041890/617FA6CE816191C38661ACA6D731162C0CB33BC7.PNG",
      "trophyGroupId": "default"
    },
    {
      "trophyId": 18,
      "trophyHidden": false,
      "trophyType": "gold",
      "trophyName": "Devil Girl",
      "trophyDetail": "Find the Devil Girl",
      "trophyIconUrl": "https://image.api.playstation.com/trophy/np/NPWR47300_00_00BC35175A41D3072912B0CBEB2EE41ABBEE041890/BC95174D4133CC18853BAA3E9B4E1E039D7A580A.PNG",
      "trophyGroupId": "default"
    },
    {
      "trophyId": 19,
      "trophyHidden": false,
      "trophyType": "gold",
      "trophyName": "Balloons",
      "trophyDetail": "Find the Balloons",
      "trophyIconUrl": "https://image.api.playstation.com/trophy/np/NPWR47300_00_00BC35175A41D3072912B0CBEB2EE41ABBEE041890/8E041E3D71324FB64FA284EE442F6FDAE345188C.PNG",
      "trophyGroupId": "default"
    },
    {
      "trophyId": 20,
      "trophyHidden": false,
      "trophyType": "gold",
      "trophyName": "Castle Gate",
      "trophyDetail": "Find the Castle Gate",
      "trophyIconUrl": "https://image.api.playstation.com/trophy/np/NPWR47300_00_00BC35175A41D3072912B0CBEB2EE41ABBEE041890/F64CE272F3272F964B18E2CF4EDF119C1D6EA4D8.PNG",
      "trophyGroupId": "default"
    },
    {
      "trophyId": 21,
      "trophyHidden": false,
      "trophyType": "gold",
      "trophyName": "Pirate",
      "trophyDetail": "Find the Pirate",
      "trophyIconUrl": "https://image.api.playstation.com/trophy/np/NPWR47300_00_00BC35175A41D3072912B0CBEB2EE41ABBEE041890/C177B8B43E1E196F8EBA749691ECA59E6CF6A508.PNG",
      "trophyGroupId": "default"
    }
  ]
}