{
  "npCommunicationId": "NPWR50109_00",
  "title": "Beat Heaven Symphony",
  "platform": "PS4",
  "trophySetVersion": "01.00",
  "hasTrophyGroups": false,
  "totalItemCount": 13,
  "trophies": [
    {
      "trophyId": 0,
      "trophyHidden": false,
      "trophyType": "platinum",
      "trophyName": "Musician",
      "trophyDetail": "Unlock all trophies",
      "trophyIconUrl": "https://image.api.playstation.com/trophy/np/NPWR50109_00_00223A27FD53DF271A56D7B6D7DE4C1456BFD8BD98/0F88A5901B21CCABD199F598B8173D4BE676B6E9.PNG",
      "trophyGroupId": "default"
    },
    {
      "trophyId": 1,
      "trophyHidden": false,
      "trophyType": "silver",
      "trophyName": "Mirage of Memories",
      "trophyDetail": "Complete the Mirage of Memories music with a success rate of 50 percent or higher",
      "trophyIconUrl": "https://image.api.playstation.com/trophy/np/NPWR50109_00_00223A27FD53DF271A56D7B6D7DE4C1456BFD8BD98/9FFB34E2616F3FD612C959B6BA85B2EF5531B3AB.PNG",
      "trophyGroupId": "default"
    },
    {
      "trophyId": 2,
      "trophyHidden": false,
      "trophyType": "gold",
      "trophyName": "Horizon",
      "trophyDetail": "Complete the Horizon music with a success rate of 50 percent or higher",
      "trophyIconUrl": "https://image.api.playstation.com/trophy/np/NPWR50109_00_00223A27FD53DF271A56D7B6D7DE4C1456BFD8BD98/5377FA4997A6921276E8D519915BA69435F19B1F.PNG",
      "trophyGroupId": "default"
    },
    {
      "trophyId": 3,
      "trophyHidden": false,
      "trophyType": "gold",
      "trophyName": "Paper Skies",
      "trophyDetail": "Complete the Paper Skies music with a success rate of 50 percent or higher",
      "trophyIconUrl": "https://image.api.playstation.com/trophy/np/NPWR50109_00_00223A27FD53DF271A56D7B6D7DE4C1456BFD8BD98/D350F21076818FB0D640DAAD97AFDFABF9B78DFB.PNG",
      "trophyGroupId": "default"
    },
    {
      "trophyId": 4,
      "trophyHidden": false,
      "trophyType": "gold",
      "trophyName": "Solstice",
      "trophyDetail": "Complete the Solstice music with a success rate of 50 percent or higher",
      "trophyIconUrl": "https://image.api.playstation.com/trophy/np/NPWR50109_00_00223A27FD53DF271A56D7B6D7DE4C1456BFD8BD98/003CA2BAE9546F02B44BC7852C00A8D985FF62C5.PNG",
      "trophyGroupId": "default"
    },
    {
      "trophyId": 5,
      "trophyHidden": false,
      "trophyType": "gold",
      "trophyName": "60 Percent",
      "trophyDetail": "Complete any music with a success rate of 60 percent or higher",
      "trophyIconUrl": "https://image.api.playstation.com/trophy/np/NPWR50109_00_00223A27FD53DF271A56D7B6D7DE4C1456BFD8BD98/759607B3EA556A9F59A787C80E11E62BE60C2F81.PNG",
      "trophyGroupId": "default"
    },
    {
      "trophyId": 6,
      "trophyHidden": false,
      "trophyType": "gold",
      "trophyName": "70 Percent",
      "trophyDetail": "Complete any music with a success rate of 70 percent or higher",
      "trophyIconUrl": "https://image.api.playstation.com/trophy/np/NPWR50109_00_00223A27FD53DF271A56D7B6D7DE4C1456BFD8BD98/3C33E552389BCEC349561A9B36674127B969D26F.PNG",
      "trophyGroupId": "default"
    },
    {
      "trophyId": 7,
      "trophyHidden": false,
      "trophyType": "gold",
      "trophyName": "30 Mistake",
      "trophyDetail": "Finish any music with 30 mistakes or less",
      "trophyIconUrl": "https://image.api.playstation.com/trophy/np/NPWR50109_00_00223A27FD53DF271A56D7B6D7DE4C1456BFD8BD98/06787E0775B7E0BB5B3B19B658551A31406DAF1F.PNG",
      "trophyGroupId": "default"
    },
    {
      "trophyId": 8,
      "trophyHidden": false,
      "trophyType": "gold",
      "trophyName": "5 Combo",
      "trophyDetail": "Hit the correct note 5 times in a row",
      "trophyIconUrl": "https://image.api.playstation.com/trophy/np/NPWR50109_00_00223A27FD53DF271A56D7B6D7DE4C1456BFD8BD98/169A8D9A485500FA2DBF40FAB0AE27A61403D92B.PNG",
      "trophyGroupId": "default"
    },
    {
      "trophyId": 9,
      "trophyHidden": false,
      "trophyType": "gold",
      "trophyName": "8 Combo",
      "trophyDetail": "Hit the correct note 8 times in a row",
      "trophyIconUrl": "https://image.api.playstation.com/trophy/np/NPWR50109_00_00223A27FD53DF271A56D7B6D7DE4C1456BFD8BD98/03DDF84BFCE73F2E67FEACCE0DD52145D56A86EB.PNG",
      "trophyGroupId": "default"
    },
    {
      "trophyId": 10,
      "trophyHidden": false,
      "trophyType": "gold",
      "trophyName": "New Music",
      "trophyDetail": "Unlock new music ",
      "trophyIconUrl": "https://image.api.playstation.com/trophy/np/NPWR50109_00_00223A27FD53DF271A56D7B6D7DE4C1456BFD8BD98/E56D010BC641FF9C14E23FCC5C25F3A7C396FB87.PNG",
      "trophyGroupId": "default"
    },
    {
      "trophyId": 11,
      "trophyHidden": false,
      "trophyType": "gold",
      "trophyName": "7500 Point",
      "trophyDetail": "Reach 7500 points in any music",
      "trophyIconUrl": "https://image.api.playstation.com/trophy/np/NPWR50109_00_00223A27FD53DF271A56D7B6D7DE4C1456BFD8BD98/86159691C34677F768F780840705BC92C05AD800.PNG",
      "trophyGroupId": "default"
    },
    {
      "trophyId": 12,
      "trophyHidden": false,
      "trophyType": "gold",
      "trophyName": "2X Multiple",
      "trophyDetail": "Reach 2X multiplier",
      "trophyIconUrl": "https://image.api.playstation.com/trophy/np/NPWR50109_00_00223A27FD53DF271A56D7B6D7DE4C1456BFD8BD98/731F496F085211D5175F6DA3672A67ADF988B55F.PNG",
      "trophyGroupId": "default"
    }
  ]
}