{
  "npCommunicationId": "NPWR54274_00",
  "title": "Italian Brainrot",
  "platform": "PS5",
  "trophySetVersion": "01.00",
  "hasTrophyGroups": false,
  "totalItemCount": 12,
  "trophies": [
    {
      "trophyId": 0,
      "trophyHidden": false,
      "trophyType": "platinum",
      "trophyName": "Its the End!",
      "trophyDetail": "Unlock all Trophies",
      "trophyIconUrl": "https://psnobj.prod.dl.playstation.net/psnobj/NPWR54274_00/bfc4df46-91e6-40e6-a608-8665ad986a56.png",
      "trophyGroupId": "default"
    },
    {
      "trophyId": 1,
      "trophyHidden": false,
      "trophyType": "gold",
      "trophyName": "1",
      "trophyDetail": "Score 1",
      "trophyIconUrl": "https://psnobj.prod.dl.playstation.net/psnobj/NPWR54274_00/d3232921-e9ca-47f7-a89d-5e834b174689.png",
      "trophyGroupId": "default"
    },
    {
      "trophyId": 2,
      "trophyHidden": false,
      "trophyType": "gold",
      "trophyName": "2",
      "trophyDetail": "Score 2",
      "trophyIconUrl": "https://psnobj.prod.dl.playstation.net/psnobj/NPWR54274_00/df7f61de-c286-49a3-b1ec-1f86678c9629.png",
      "trophyGroupId": "default"
    },
    {
      "trophyId": 3,
      "trophyHidden": false,
      "trophyType": "gold",
      "trophyName": "3",
      "trophyDetail": "Score 3",
      "trophyIconUrl": "https://psnobj.prod.dl.playstation.net/psnobj/NPWR54274_00/39f1884a-6191-4284-a725-4fb34bf720b5.png",
      "trophyGroupId": "default"
    },
    {
      "trophyId": 4,
      "trophyHidden": false,
      "trophyType": "gold",
      "trophyName": "4",
      "trophyDetail": "Score 4",
      "trophyIconUrl": "https://psnobj.prod.dl.playstation.net/psnobj/NPWR54274_00/6ee1e26a-1d9f-45b8-9682-35db7427ec3d.png",
      "trophyGroupId": "default"
    },
    {
      "trophyId": 5,
      "trophyHidden": false,
      "trophyType": "gold",
      "trophyName": "5",
      "trophyDetail": "Score 5",
      "trophyIconUrl": "https://psnobj.prod.dl.playstation.net/psnobj/NPWR54274_00/654fd32e-e572-4375-ba81-33a463c478f0.png",
      "trophyGroupId": "default"
    },
    {
      "trophyId": 6,
      "trophyHidden": false,
      "trophyType": "gold",
      "trophyName": "6",
      "trophyDetail": "Score 6",
      "trophyIconUrl": "https://psnobj.prod.dl.playstation.net/psnobj/NPWR54274_00/d55edfc6-8bc2-4908-83b2-3844dfd7bee9.png",
      "trophyGroupId": "default"
    },
    {
      "trophyId": 7,
      "trophyHidden": false,
      "trophyType": "gold",
      "trophyName": "7",
      "trophyDetail": "Score 7",
      "trophyIconUrl": "https://psnobj.prod.dl.playstation.net/psnobj/NPWR54274_00/efd19117-2914-4770-8c6e-72b1cb63cba3.png",
      "trophyGroupId": "default"
    },
    {
      "trophyId": 8,
      "trophyHidden": false,
      "trophyType": "gold",
      "trophyName": "8",
      "trophyDetail": "Score 8",
      "trophyIconUrl": "https://psnobj.prod.dl.playstation.net/psnobj/NPWR54274_00/93901148-a241-4af2-adaf-b8d331ce06cb.png",
      "trophyGroupId": "default"
    },
    {
      "trophyId": 9,
      "trophyHidden": false,
      "trophyType": "gold",
      "trophyName": "9",
      "trophyDetail": "Score 9",
      "trophyIconUrl": "https://psnobj.prod.dl.playstation.net/psnobj/NPWR54274_00/0cba5806-ea15-4fa5-be1c-048894b8a44a.png",
      "trophyGroupId": "default"
    },
    {
      "trophyId": 10,
      "trophyHidden": false,
      "trophyType": "gold",
      "trophyName": "10",
      "trophyDetail": "Score 10",
      "trophyIconUrl": "https://psnobj.prod.dl.playstation.net/psnobj/NPWR54274_00/3e0512bf-b577-4829-8c87-2ea7e00b853d.png",
      "trophyGroupId": "default"
    },
    {
      "trophyId": 11,
      "trophyHidden": false,
      "trophyType": "gold",
      "trophyName": "11",
      "trophyDetail": "Score 11",
      "trophyIconUrl": "https://psnobj.prod.dl.playstation.net/psnobj/NPWR54274_00/078f5324-3dcd-4404-a709-f2461306d5e3.png",
      "trophyGroupId": "default"
    }
  ]
}