{
  "npCommunicationId": "NPWR51947_00",
  "title": "Stasis",
  "platform": "PS5",
  "trophySetVersion": "01.00",
  "hasTrophyGroups": false,
  "totalItemCount": 27,
  "trophies": [
    {
      "trophyId": 0,
      "trophyHidden": false,
      "trophyType": "bronze",
      "trophyName": "Jupiter Dies",
      "trophyDetail": "Corner the cat",
      "trophyIconUrl": "https://psnobj.prod.dl.playstation.net/psnobj/NPWR51947_00/0805b0e2-e2b4-4514-905f-0e839214c0fa.png",
      "trophyGroupId": "default"
    },
    {
      "trophyId": 1,
      "trophyHidden": false,
      "trophyType": "bronze",
      "trophyName": "Jump?!",
      "trophyDetail": "Escape the fallen tram",
      "trophyIconUrl": "https://psnobj.prod.dl.playstation.net/psnobj/NPWR51947_00/a5d68b1b-97a2-44d7-a972-9b37e65038cb.png",
      "trophyGroupId": "default"
    },
    {
      "trophyId": 2,
      "trophyHidden": false,
      "trophyType": "bronze",
      "trophyName": "Why Are There Methane Tanks under the Crew Quaters",
      "trophyDetail": "Clear the debris blocking the elevator",
      "trophyIconUrl": "https://psnobj.prod.dl.playstation.net/psnobj/NPWR51947_00/1d794b06-b753-4968-941d-688928c78456.png",
      "trophyGroupId": "default"
    },
    {
      "trophyId": 3,
      "trophyHidden": false,
      "trophyType": "silver",
      "trophyName": "Subject is Alive, Deceased, Alive",
      "trophyDetail": "Survive surgery",
      "trophyIconUrl": "https://psnobj.prod.dl.playstation.net/psnobj/NPWR51947_00/800cc6a2-2bb3-4e11-903f-64d9b8f9990b.png",
      "trophyGroupId": "default"
    },
    {
      "trophyId": 4,
      "trophyHidden": false,
      "trophyType": "bronze",
      "trophyName": "Gardening",
      "trophyDetail": "Clear the vines in hydroponics",
      "trophyIconUrl": "https://psnobj.prod.dl.playstation.net/psnobj/NPWR51947_00/f2641799-082d-414c-a2a4-f0f171c0aa72.png",
      "trophyGroupId": "default"
    },
    {
      "trophyId": 5,
      "trophyHidden": false,
      "trophyType": "bronze",
      "trophyName": "Mercy",
      "trophyDetail": "End the suffering of the pregnat woman",
      "trophyIconUrl": "https://psnobj.prod.dl.playstation.net/psnobj/NPWR51947_00/aa137349-6177-4faf-8df5-3044a1cc3625.png",
      "trophyGroupId": "default"
    },
    {
      "trophyId": 6,
      "trophyHidden": false,
      "trophyType": "bronze",
      "trophyName": "Stomp",
      "trophyDetail": "Foot stomp a hybrid",
      "trophyIconUrl": "https://psnobj.prod.dl.playstation.net/psnobj/NPWR51947_00/9827ab3b-b63c-4fa4-857e-b3ab6ea50de3.png",
      "trophyGroupId": "default"
    },
    {
      "trophyId": 7,
      "trophyHidden": false,
      "trophyType": "bronze",
      "trophyName": "A History Lesson",
      "trophyDetail": "Enjoy a tour of the visitor center",
      "trophyIconUrl": "https://psnobj.prod.dl.playstation.net/psnobj/NPWR51947_00/7ff887f1-44e1-48f0-8f0b-64caed51b716.png",
      "trophyGroupId": "default"
    },
    {
      "trophyId": 8,
      "trophyHidden": false,
      "trophyType": "bronze",
      "trophyName": "Dissolved",
      "trophyDetail": "Death",
      "trophyIconUrl": "https://psnobj.prod.dl.playstation.net/psnobj/NPWR51947_00/5676f459-5db3-41e3-b345-bdb1f88bc54f.png",
      "trophyGroupId": "default"
    },
    {
      "trophyId": 9,
      "trophyHidden": false,
      "trophyType": "bronze",
      "trophyName": "Eaten",
      "trophyDetail": "Death",
      "trophyIconUrl": "https://psnobj.prod.dl.playstation.net/psnobj/NPWR51947_00/899958cd-21a5-4881-afa8-6f9a7dd1c073.png",
      "trophyGroupId": "default"
    },
    {
      "trophyId": 10,
      "trophyHidden": false,
      "trophyType": "bronze",
      "trophyName": "Melted",
      "trophyDetail": "Death",
      "trophyIconUrl": "https://psnobj.prod.dl.playstation.net/psnobj/NPWR51947_00/33085763-c102-40c3-983b-22e154d761c5.png",
      "trophyGroupId": "default"
    },
    {
      "trophyId": 11,
      "trophyHidden": false,
      "trophyType": "bronze",
      "trophyName": "Gassed",
      "trophyDetail": "Death",
      "trophyIconUrl": "https://psnobj.prod.dl.playstation.net/psnobj/NPWR51947_00/4431da13-8c6a-4c25-8791-7bde40671b7d.png",
      "trophyGroupId": "default"
    },
    {
      "trophyId": 12,
      "trophyHidden": false,
      "trophyType": "bronze",
      "trophyName": "Blown up",
      "trophyDetail": "Death",
      "trophyIconUrl": "https://psnobj.prod.dl.playstation.net/psnobj/NPWR51947_00/1107eff6-9cde-4564-b84a-ca327c83d5ae.png",
      "trophyGroupId": "default"
    },
    {
      "trophyId": 13,
      "trophyHidden": false,
      "trophyType": "bronze",
      "trophyName": "Shredded",
      "trophyDetail": "Death",
      "trophyIconUrl": "https://psnobj.prod.dl.playstation.net/psnobj/NPWR51947_00/2e722bf8-f845-45c4-ad82-a27eebe67ee4.png",
      "trophyGroupId": "default"
    },
    {
      "trophyId": 14,
      "trophyHidden": false,
      "trophyType": "bronze",
      "trophyName": "Crossfire",
      "trophyDetail": "Death",
      "trophyIconUrl": "https://psnobj.prod.dl.playstation.net/psnobj/NPWR51947_00/7c3a63a0-a4e4-43c0-8bc4-b407f9842df6.png",
      "trophyGroupId": "default"
    },
    {
      "trophyId": 15,
      "trophyHidden": false,
      "trophyType": "bronze",
      "trophyName": "Fried",
      "trophyDetail": "Death",
      "trophyIconUrl": "https://psnobj.prod.dl.playstation.net/psnobj/NPWR51947_00/9c84301c-62ab-459c-86d9-39065ef03a17.png",
      "trophyGroupId": "default"
    },
    {
      "trophyId": 16,
      "trophyHidden": false,
      "trophyType": "bronze",
      "trophyName": "Bag",
      "trophyDetail": "Death",
      "trophyIconUrl": "https://psnobj.prod.dl.playstation.net/psnobj/NPWR51947_00/675dc862-85d5-4aba-a119-1945a1068295.png",
      "trophyGroupId": "default"
    },
    {
      "trophyId": 17,
      "trophyHidden": false,
      "trophyType": "bronze",
      "trophyName": "A Hole in My Head",
      "trophyDetail": "Item Surprise",
      "trophyIconUrl": "https://psnobj.prod.dl.playstation.net/psnobj/NPWR51947_00/8fbe4e5a-aab9-49c8-a8dd-36e76dbc135e.png",
      "trophyGroupId": "default"
    },
    {
      "trophyId": 18,
      "trophyHidden": false,
      "trophyType": "bronze",
      "trophyName": "Bleeding Belly",
      "trophyDetail": "Item Surprise",
      "trophyIconUrl": "https://psnobj.prod.dl.playstation.net/psnobj/NPWR51947_00/4d6709d8-d72c-4265-b7cd-fe9f199f75c0.png",
      "trophyGroupId": "default"
    },
    {
      "trophyId": 19,
      "trophyHidden": false,
      "trophyType": "bronze",
      "trophyName": "Cold Steel",
      "trophyDetail": "Item Surprise",
      "trophyIconUrl": "https://psnobj.prod.dl.playstation.net/psnobj/NPWR51947_00/882633b2-6874-4e25-9ae1-a3e756057ee1.png",
      "trophyGroupId": "default"
    },
    {
      "trophyId": 20,
      "trophyHidden": false,
      "trophyType": "silver",
      "trophyName": "Slug Gun Fight",
      "trophyDetail": "Item Surprise",
      "trophyIconUrl": "https://psnobj.prod.dl.playstation.net/psnobj/NPWR51947_00/b6331b56-ac75-4e60-a5f0-847bf1561ab9.png",
      "trophyGroupId": "default"
    },
    {
      "trophyId": 21,
      "trophyHidden": false,
      "trophyType": "silver",
      "trophyName": "I Have No Mouth but I Must Scream",
      "trophyDetail": "Item Surprise",
      "trophyIconUrl": "https://psnobj.prod.dl.playstation.net/psnobj/NPWR51947_00/786a1858-e7a2-4f2e-be8e-ae5d7ccd47f9.png",
      "trophyGroupId": "default"
    },
    {
      "trophyId": 22,
      "trophyHidden": false,
      "trophyType": "silver",
      "trophyName": "It Burns",
      "trophyDetail": "Item Surprise",
      "trophyIconUrl": "https://psnobj.prod.dl.playstation.net/psnobj/NPWR51947_00/3b9221de-8391-4ac6-b37c-794bda4b97c7.png",
      "trophyGroupId": "default"
    },
    {
      "trophyId": 23,
      "trophyHidden": false,
      "trophyType": "silver",
      "trophyName": "Hangman",
      "trophyDetail": "Item Suprise",
      "trophyIconUrl": "https://psnobj.prod.dl.playstation.net/psnobj/NPWR51947_00/9eec9314-ecbd-4447-b205-0347f12eee5d.png",
      "trophyGroupId": "default"
    },
    {
      "trophyId": 24,
      "trophyHidden": false,
      "trophyType": "silver",
      "trophyName": "Plasma Overload",
      "trophyDetail": "Item Suprise",
      "trophyIconUrl": "https://psnobj.prod.dl.playstation.net/psnobj/NPWR51947_00/873f63f5-e1a4-44c1-82dd-9730e5ae3826.png",
      "trophyGroupId": "default"
    },
    {
      "trophyId": 25,
      "trophyHidden": false,
      "trophyType": "silver",
      "trophyName": "Opening Break Shot",
      "trophyDetail": "Item Suprise",
      "trophyIconUrl": "https://psnobj.prod.dl.playstation.net/psnobj/NPWR51947_00/a5eabbfb-b08b-45c5-af12-a8155ca42fff.png",
      "trophyGroupId": "default"
    },
    {
      "trophyId": 26,
      "trophyHidden": false,
      "trophyType": "gold",
      "trophyName": "I Love You Ellen",
      "trophyDetail": "Complete STASIS",
      "trophyIconUrl": "https://psnobj.prod.dl.playstation.net/psnobj/NPWR51947_00/232aca01-2ccb-43d6-bb40-cf51f6a2b00e.png",
      "trophyGroupId": "default"
    }
  ]
}