{
  "npCommunicationId": "NPWR52904_00",
  "title": "The Jumping Shaped Fries",
  "platform": "PS4",
  "trophySetVersion": "01.00",
  "hasTrophyGroups": false,
  "totalItemCount": 71,
  "trophies": [
    {
      "trophyId": 0,
      "trophyHidden": false,
      "trophyType": "platinum",
      "trophyName": "Fries in shape",
      "trophyDetail": "Collect all other trophies.",
      "trophyIconUrl": "https://image.api.playstation.com/trophy/np/NPWR52904_00_0073B51C08673F152F6BA19616EFA16E248A990142/56073047880651A347EDB3BA054458915C4539A2.PNG",
      "trophyGroupId": "default"
    },
    {
      "trophyId": 1,
      "trophyHidden": false,
      "trophyType": "bronze",
      "trophyName": "Reach 50 points in total",
      "trophyDetail": "Reach 50 points in total.",
      "trophyIconUrl": "https://image.api.playstation.com/trophy/np/NPWR52904_00_0073B51C08673F152F6BA19616EFA16E248A990142/65C89E9642D082A99E6DF08DD433C4957D7357AB.PNG",
      "trophyGroupId": "default"
    },
    {
      "trophyId": 2,
      "trophyHidden": false,
      "trophyType": "bronze",
      "trophyName": "Reach 100 points in total",
      "trophyDetail": "Reach 100 points in total.",
      "trophyIconUrl": "https://image.api.playstation.com/trophy/np/NPWR52904_00_0073B51C08673F152F6BA19616EFA16E248A990142/35A07D1A02AB579C51C13C314EE6CD228F9FA4CE.PNG",
      "trophyGroupId": "default"
    },
    {
      "trophyId": 3,
      "trophyHidden": false,
      "trophyType": "bronze",
      "trophyName": "Reach 150 points in total",
      "trophyDetail": "Reach 150 points in total.",
      "trophyIconUrl": "https://image.api.playstation.com/trophy/np/NPWR52904_00_0073B51C08673F152F6BA19616EFA16E248A990142/D531E34B1895DD3015A34E615426E0F347879955.PNG",
      "trophyGroupId": "default"
    },
    {
      "trophyId": 4,
      "trophyHidden": false,
      "trophyType": "bronze",
      "trophyName": "Reach 200 points in total",
      "trophyDetail": "Reach 200 points in total.",
      "trophyIconUrl": "https://image.api.playstation.com/trophy/np/NPWR52904_00_0073B51C08673F152F6BA19616EFA16E248A990142/61C60D2E674C3057BD3D4DF7A958013A3AF8632C.PNG",
      "trophyGroupId": "default"
    },
    {
      "trophyId": 5,
      "trophyHidden": false,
      "trophyType": "bronze",
      "trophyName": "Reach 250 points in total",
      "trophyDetail": "Reach 250 points in total.",
      "trophyIconUrl": "https://image.api.playstation.com/trophy/np/NPWR52904_00_0073B51C08673F152F6BA19616EFA16E248A990142/F4FD0B17E93665B2621F2F264C59ED17EB19AF17.PNG",
      "trophyGroupId": "default"
    },
    {
      "trophyId": 6,
      "trophyHidden": false,
      "trophyType": "bronze",
      "trophyName": "Reach 300 points in total",
      "trophyDetail": "Reach 300 points in total.",
      "trophyIconUrl": "https://image.api.playstation.com/trophy/np/NPWR52904_00_0073B51C08673F152F6BA19616EFA16E248A990142/08547E4F67D5E4C4054972807C47CF25FEC1A1B4.PNG",
      "trophyGroupId": "default"
    },
    {
      "trophyId": 7,
      "trophyHidden": false,
      "trophyType": "bronze",
      "trophyName": "Reach 350 points in total",
      "trophyDetail": "Reach 350 points in total.",
      "trophyIconUrl": "https://image.api.playstation.com/trophy/np/NPWR52904_00_0073B51C08673F152F6BA19616EFA16E248A990142/7BA896063A6EE33F310749E4A54209159310F22E.PNG",
      "trophyGroupId": "default"
    },
    {
      "trophyId": 8,
      "trophyHidden": false,
      "trophyType": "bronze",
      "trophyName": "Reach 400 points in total",
      "trophyDetail": "Reach 400 points in total.",
      "trophyIconUrl": "https://image.api.playstation.com/trophy/np/NPWR52904_00_0073B51C08673F152F6BA19616EFA16E248A990142/89ADC7004EA399B206FADE480920EAF75EA63427.PNG",
      "trophyGroupId": "default"
    },
    {
      "trophyId": 9,
      "trophyHidden": false,
      "trophyType": "bronze",
      "trophyName": "Reach 450 points in total",
      "trophyDetail": "Reach 450 points in total.",
      "trophyIconUrl": "https://image.api.playstation.com/trophy/np/NPWR52904_00_0073B51C08673F152F6BA19616EFA16E248A990142/5B3D032FD3F08C6E536DA0D345908CDEBF91E133.PNG",
      "trophyGroupId": "default"
    },
    {
      "trophyId": 10,
      "trophyHidden": false,
      "trophyType": "bronze",
      "trophyName": "Reach 500 points in total",
      "trophyDetail": "Reach 500 points in total.",
      "trophyIconUrl": "https://image.api.playstation.com/trophy/np/NPWR52904_00_0073B51C08673F152F6BA19616EFA16E248A990142/88418900F6256DCCB1A993F1CD9032FD30826846.PNG",
      "trophyGroupId": "default"
    },
    {
      "trophyId": 11,
      "trophyHidden": false,
      "trophyType": "bronze",
      "trophyName": "Reach 550 points in total",
      "trophyDetail": "Reach 550 points in total.",
      "trophyIconUrl": "https://image.api.playstation.com/trophy/np/NPWR52904_00_0073B51C08673F152F6BA19616EFA16E248A990142/1CF408C16DEEE6B1DA6196264A4ADA104D6955B7.PNG",
      "trophyGroupId": "default"
    },
    {
      "trophyId": 12,
      "trophyHidden": false,
      "trophyType": "bronze",
      "trophyName": "Reach 600 points in total",
      "trophyDetail": "Reach 600 points in total.",
      "trophyIconUrl": "https://image.api.playstation.com/trophy/np/NPWR52904_00_0073B51C08673F152F6BA19616EFA16E248A990142/7A2C00765FF9C7596BC7FDA666D5D90488B42176.PNG",
      "trophyGroupId": "default"
    },
    {
      "trophyId": 13,
      "trophyHidden": false,
      "trophyType": "bronze",
      "trophyName": "Reach 650 points in total",
      "trophyDetail": "Reach 650 points in total.",
      "trophyIconUrl": "https://image.api.playstation.com/trophy/np/NPWR52904_00_0073B51C08673F152F6BA19616EFA16E248A990142/677E8DBBC2788F276D32CB95213166242F7436DD.PNG",
      "trophyGroupId": "default"
    },
    {
      "trophyId": 14,
      "trophyHidden": false,
      "trophyType": "bronze",
      "trophyName": "Reach 700 points in total",
      "trophyDetail": "Reach 700 points in total.",
      "trophyIconUrl": "https://image.api.playstation.com/trophy/np/NPWR52904_00_0073B51C08673F152F6BA19616EFA16E248A990142/02EF90F851E565F0183402F48ABA03AA33A54D8C.PNG",
      "trophyGroupId": "default"
    },
    {
      "trophyId": 15,
      "trophyHidden": false,
      "trophyType": "bronze",
      "trophyName": "Reach 750 points in total",
      "trophyDetail": "Reach 750 points in total.",
      "trophyIconUrl": "https://image.api.playstation.com/trophy/np/NPWR52904_00_0073B51C08673F152F6BA19616EFA16E248A990142/58B7282E7DAB346BD2743702538E8530E181F26A.PNG",
      "trophyGroupId": "default"
    },
    {
      "trophyId": 16,
      "trophyHidden": false,
      "trophyType": "bronze",
      "trophyName": "Reach 800 points in total",
      "trophyDetail": "Reach 800 points in total.",
      "trophyIconUrl": "https://image.api.playstation.com/trophy/np/NPWR52904_00_0073B51C08673F152F6BA19616EFA16E248A990142/66EAAEDB68D16248E7A035C2FB139C31C4A2E607.PNG",
      "trophyGroupId": "default"
    },
    {
      "trophyId": 17,
      "trophyHidden": false,
      "trophyType": "bronze",
      "trophyName": "Reach 850 points in total",
      "trophyDetail": "Reach 850 points in total.",
      "trophyIconUrl": "https://image.api.playstation.com/trophy/np/NPWR52904_00_0073B51C08673F152F6BA19616EFA16E248A990142/A3F530DBBC3BCAC132ED180672A14F98B43BFA1E.PNG",
      "trophyGroupId": "default"
    },
    {
      "trophyId": 18,
      "trophyHidden": false,
      "trophyType": "bronze",
      "trophyName": "Reach 900 points in total",
      "trophyDetail": "Reach 900 points in total.",
      "trophyIconUrl": "https://image.api.playstation.com/trophy/np/NPWR52904_00_0073B51C08673F152F6BA19616EFA16E248A990142/4B4AC033E3EA1799D603C923BDA32565272D0064.PNG",
      "trophyGroupId": "default"
    },
    {
      "trophyId": 19,
      "trophyHidden": false,
      "trophyType": "bronze",
      "trophyName": "Reach 950 points in total",
      "trophyDetail": "Reach 950 points in total.",
      "trophyIconUrl": "https://image.api.playstation.com/trophy/np/NPWR52904_00_0073B51C08673F152F6BA19616EFA16E248A990142/F06B44C13704C61E3300D21789B043BD3892A670.PNG",
      "trophyGroupId": "default"
    },
    {
      "trophyId": 20,
      "trophyHidden": false,
      "trophyType": "bronze",
      "trophyName": "Reach 1.000 points in total",
      "trophyDetail": "Reach 1.000 points in total.",
      "trophyIconUrl": "https://image.api.playstation.com/trophy/np/NPWR52904_00_0073B51C08673F152F6BA19616EFA16E248A990142/63A1075515C10BC909CB99040635CD2227879A34.PNG",
      "trophyGroupId": "default"
    },
    {
      "trophyId": 21,
      "trophyHidden": false,
      "trophyType": "bronze",
      "trophyName": "Reach 1.050 points in total",
      "trophyDetail": "Reach 1.050 points in total.",
      "trophyIconUrl": "https://image.api.playstation.com/trophy/np/NPWR52904_00_0073B51C08673F152F6BA19616EFA16E248A990142/22791270D794ACE69780FF89EDDB048D9190607B.PNG",
      "trophyGroupId": "default"
    },
    {
      "trophyId": 22,
      "trophyHidden": false,
      "trophyType": "bronze",
      "trophyName": "Reach 1.100 points in total",
      "trophyDetail": "Reach 1.100 points in total.",
      "trophyIconUrl": "https://image.api.playstation.com/trophy/np/NPWR52904_00_0073B51C08673F152F6BA19616EFA16E248A990142/C5ACBE6DF8F8A1C593E0A91A8CD39795A6098D15.PNG",
      "trophyGroupId": "default"
    },
    {
      "trophyId": 23,
      "trophyHidden": false,
      "trophyType": "bronze",
      "trophyName": "Reach 1.150 points in total",
      "trophyDetail": "Reach 1.150 points in total.",
      "trophyIconUrl": "https://image.api.playstation.com/trophy/np/NPWR52904_00_0073B51C08673F152F6BA19616EFA16E248A990142/3DF97C74BBB7198CDF9D986FB47F0B33AD0E3101.PNG",
      "trophyGroupId": "default"
    },
    {
      "trophyId": 24,
      "trophyHidden": false,
      "trophyType": "bronze",
      "trophyName": "Reach 1.200 points in total",
      "trophyDetail": "Reach 1.200 points in total.",
      "trophyIconUrl": "https://image.api.playstation.com/trophy/np/NPWR52904_00_0073B51C08673F152F6BA19616EFA16E248A990142/EC1160493BA3E522A93814FD4EEB09FF2552A062.PNG",
      "trophyGroupId": "default"
    },
    {
      "trophyId": 25,
      "trophyHidden": false,
      "trophyType": "bronze",
      "trophyName": "Reach 1.250 points in total",
      "trophyDetail": "Reach 1.250 points in total.",
      "trophyIconUrl": "https://image.api.playstation.com/trophy/np/NPWR52904_00_0073B51C08673F152F6BA19616EFA16E248A990142/E8D2EF6B5D93EF056579ED47455CE4D44F25193A.PNG",
      "trophyGroupId": "default"
    },
    {
      "trophyId": 26,
      "trophyHidden": false,
      "trophyType": "bronze",
      "trophyName": "Reach 1.300 points in total",
      "trophyDetail": "Reach 1.300 points in total.",
      "trophyIconUrl": "https://image.api.playstation.com/trophy/np/NPWR52904_00_0073B51C08673F152F6BA19616EFA16E248A990142/BCC52E89E63E65C59E1576BA0AD874DDB0A07A07.PNG",
      "trophyGroupId": "default"
    },
    {
      "trophyId": 27,
      "trophyHidden": false,
      "trophyType": "bronze",
      "trophyName": "Reach 1.350 points in total",
      "trophyDetail": "Reach 1.350 points in total.",
      "trophyIconUrl": "https://image.api.playstation.com/trophy/np/NPWR52904_00_0073B51C08673F152F6BA19616EFA16E248A990142/0A18C7C697E330F0F977E80B711F85CB7B3B0F41.PNG",
      "trophyGroupId": "default"
    },
    {
      "trophyId": 28,
      "trophyHidden": false,
      "trophyType": "bronze",
      "trophyName": "Reach 1.400 points in total",
      "trophyDetail": "Reach 1.400 points in total.",
      "trophyIconUrl": "https://image.api.playstation.com/trophy/np/NPWR52904_00_0073B51C08673F152F6BA19616EFA16E248A990142/449ADA389B9AE09085E6F4F7B9B5D9877172129D.PNG",
      "trophyGroupId": "default"
    },
    {
      "trophyId": 29,
      "trophyHidden": false,
      "trophyType": "bronze",
      "trophyName": "Reach 1.450 points in total",
      "trophyDetail": "Reach 1.450 points in total.",
      "trophyIconUrl": "https://image.api.playstation.com/trophy/np/NPWR52904_00_0073B51C08673F152F6BA19616EFA16E248A990142/3A33BB5339C0330EF2D89E3D129392D586B0F10A.PNG",
      "trophyGroupId": "default"
    },
    {
      "trophyId": 30,
      "trophyHidden": false,
      "trophyType": "bronze",
      "trophyName": "Reach 1.500 points in total",
      "trophyDetail": "Reach 1.500 points in total.",
      "trophyIconUrl": "https://image.api.playstation.com/trophy/np/NPWR52904_00_0073B51C08673F152F6BA19616EFA16E248A990142/2E7741D7111BF34F9997649D463F993A4B4EAF03.PNG",
      "trophyGroupId": "default"
    },
    {
      "trophyId": 31,
      "trophyHidden": false,
      "trophyType": "bronze",
      "trophyName": "Reach 1.550 points in total",
      "trophyDetail": "Reach 1.550 points in total.",
      "trophyIconUrl": "https://image.api.playstation.com/trophy/np/NPWR52904_00_0073B51C08673F152F6BA19616EFA16E248A990142/E9C1B0B1742257D25B607AD3625379A90A05909B.PNG",
      "trophyGroupId": "default"
    },
    {
      "trophyId": 32,
      "trophyHidden": false,
      "trophyType": "bronze",
      "trophyName": "Reach 1.600 points in total",
      "trophyDetail": "Reach 1.600 points in total.",
      "trophyIconUrl": "https://image.api.playstation.com/trophy/np/NPWR52904_00_0073B51C08673F152F6BA19616EFA16E248A990142/DC8CCAB4102D33D0E629A820A25CEF051E71C4AD.PNG",
      "trophyGroupId": "default"
    },
    {
      "trophyId": 33,
      "trophyHidden": false,
      "trophyType": "bronze",
      "trophyName": "Reach 1.650 points in total",
      "trophyDetail": "Reach 1.650 points in total.",
      "trophyIconUrl": "https://image.api.playstation.com/trophy/np/NPWR52904_00_0073B51C08673F152F6BA19616EFA16E248A990142/064E81DC9642C426B20D0B3E7265F83303D71D1E.PNG",
      "trophyGroupId": "default"
    },
    {
      "trophyId": 34,
      "trophyHidden": false,
      "trophyType": "bronze",
      "trophyName": "Reach 1.700 points in total",
      "trophyDetail": "Reach 1.700 points in total.",
      "trophyIconUrl": "https://image.api.playstation.com/trophy/np/NPWR52904_00_0073B51C08673F152F6BA19616EFA16E248A990142/04166E580EFD2BC99D326ADBA74D8B78E543243D.PNG",
      "trophyGroupId": "default"
    },
    {
      "trophyId": 35,
      "trophyHidden": false,
      "trophyType": "bronze",
      "trophyName": "Reach 1.750 points in total",
      "trophyDetail": "Reach 1.750 points in total.",
      "trophyIconUrl": "https://image.api.playstation.com/trophy/np/NPWR52904_00_0073B51C08673F152F6BA19616EFA16E248A990142/76A7C0E3F15D8B48EBB10C9F5D06841D59A1205B.PNG",
      "trophyGroupId": "default"
    },
    {
      "trophyId": 36,
      "trophyHidden": false,
      "trophyType": "bronze",
      "trophyName": "Reach 1.800 points in total",
      "trophyDetail": "Reach 1.800 points in total.",
      "trophyIconUrl": "https://image.api.playstation.com/trophy/np/NPWR52904_00_0073B51C08673F152F6BA19616EFA16E248A990142/0A65A34515DA79370927A037C4BFC3E2508838A2.PNG",
      "trophyGroupId": "default"
    },
    {
      "trophyId": 37,
      "trophyHidden": false,
      "trophyType": "bronze",
      "trophyName": "Reach 1.850 points in total",
      "trophyDetail": "Reach 1.850 points in total.",
      "trophyIconUrl": "https://image.api.playstation.com/trophy/np/NPWR52904_00_0073B51C08673F152F6BA19616EFA16E248A990142/1C5570CE8A1B5F83E9022047CA8384A47909F8B9.PNG",
      "trophyGroupId": "default"
    },
    {
      "trophyId": 38,
      "trophyHidden": false,
      "trophyType": "bronze",
      "trophyName": "Reach 1.900 points in total",
      "trophyDetail": "Reach 1.900 points in total.",
      "trophyIconUrl": "https://image.api.playstation.com/trophy/np/NPWR52904_00_0073B51C08673F152F6BA19616EFA16E248A990142/26834F78DED2A006D03BBE6BE1EE61463192A77C.PNG",
      "trophyGroupId": "default"
    },
    {
      "trophyId": 39,
      "trophyHidden": false,
      "trophyType": "bronze",
      "trophyName": "Reach 1.950 points in total",
      "trophyDetail": "Reach 1.950 points in total.",
      "trophyIconUrl": "https://image.api.playstation.com/trophy/np/NPWR52904_00_0073B51C08673F152F6BA19616EFA16E248A990142/41BC1D5E4BDA31A2B72BDD243BAEBBC82307C94E.PNG",
      "trophyGroupId": "default"
    },
    {
      "trophyId": 40,
      "trophyHidden": false,
      "trophyType": "bronze",
      "trophyName": "Reach 2.000 points in total",
      "trophyDetail": "Reach 2.000 points in total.",
      "trophyIconUrl": "https://image.api.playstation.com/trophy/np/NPWR52904_00_0073B51C08673F152F6BA19616EFA16E248A990142/BA2B1E47762441F15B698B7C002A60967F5E3D56.PNG",
      "trophyGroupId": "default"
    },
    {
      "trophyId": 41,
      "trophyHidden": false,
      "trophyType": "bronze",
      "trophyName": "Reach 2.050 points in total",
      "trophyDetail": "Reach 2.050 points in total.",
      "trophyIconUrl": "https://image.api.playstation.com/trophy/np/NPWR52904_00_0073B51C08673F152F6BA19616EFA16E248A990142/BD83F239CAA04168C46F7429F57E5C396150ADE5.PNG",
      "trophyGroupId": "default"
    },
    {
      "trophyId": 42,
      "trophyHidden": false,
      "trophyType": "bronze",
      "trophyName": "Reach 2.100 points in total",
      "trophyDetail": "Reach 2.100 points in total.",
      "trophyIconUrl": "https://image.api.playstation.com/trophy/np/NPWR52904_00_0073B51C08673F152F6BA19616EFA16E248A990142/E8EC55AF5CE98FFCD77EE4565F31750CF5EAC9A6.PNG",
      "trophyGroupId": "default"
    },
    {
      "trophyId": 43,
      "trophyHidden": false,
      "trophyType": "bronze",
      "trophyName": "Reach 2.150 points in total",
      "trophyDetail": "Reach 2.150 points in total.",
      "trophyIconUrl": "https://image.api.playstation.com/trophy/np/NPWR52904_00_0073B51C08673F152F6BA19616EFA16E248A990142/B10A3D71E4A28A8BBAB3C69817308EA3CAEBDBFC.PNG",
      "trophyGroupId": "default"
    },
    {
      "trophyId": 44,
      "trophyHidden": false,
      "trophyType": "bronze",
      "trophyName": "Reach 2.200 points in total",
      "trophyDetail": "Reach 2.200 points in total.",
      "trophyIconUrl": "https://image.api.playstation.com/trophy/np/NPWR52904_00_0073B51C08673F152F6BA19616EFA16E248A990142/1A0F84FB8649F8504F4089739E3A34EC8F159F8B.PNG",
      "trophyGroupId": "default"
    },
    {
      "trophyId": 45,
      "trophyHidden": false,
      "trophyType": "bronze",
      "trophyName": "Reach 2.250 points in total",
      "trophyDetail": "Reach 2.250 points in total.",
      "trophyIconUrl": "https://image.api.playstation.com/trophy/np/NPWR52904_00_0073B51C08673F152F6BA19616EFA16E248A990142/3E6F755249F703C3FAF7F27BA687D7E0C7312720.PNG",
      "trophyGroupId": "default"
    },
    {
      "trophyId": 46,
      "trophyHidden": false,
      "trophyType": "bronze",
      "trophyName": "Reach 2.300 points in total",
      "trophyDetail": "Reach 2.300 points in total.",
      "trophyIconUrl": "https://image.api.playstation.com/trophy/np/NPWR52904_00_0073B51C08673F152F6BA19616EFA16E248A990142/1560F9C4982968E3F4DDFEADE3801E5FA2768424.PNG",
      "trophyGroupId": "default"
    },
    {
      "trophyId": 47,
      "trophyHidden": false,
      "trophyType": "bronze",
      "trophyName": "Reach 2.350 points in total",
      "trophyDetail": "Reach 2.350 points in total.",
      "trophyIconUrl": "https://image.api.playstation.com/trophy/np/NPWR52904_00_0073B51C08673F152F6BA19616EFA16E248A990142/D2CA084EF15A03EC7735D4D940A6256DD47B3694.PNG",
      "trophyGroupId": "default"
    },
    {
      "trophyId": 48,
      "trophyHidden": false,
      "trophyType": "bronze",
      "trophyName": "Reach 2.400 points in total",
      "trophyDetail": "Reach 2.400 points in total.",
      "trophyIconUrl": "https://image.api.playstation.com/trophy/np/NPWR52904_00_0073B51C08673F152F6BA19616EFA16E248A990142/7AA4141C2F66575FD9EACB3D4AC4382DF3F65A4F.PNG",
      "trophyGroupId": "default"
    },
    {
      "trophyId": 49,
      "trophyHidden": false,
      "trophyType": "bronze",
      "trophyName": "Reach 2.450 points in total",
      "trophyDetail": "Reach 2.450 points in total.",
      "trophyIconUrl": "https://image.api.playstation.com/trophy/np/NPWR52904_00_0073B51C08673F152F6BA19616EFA16E248A990142/4C425B8C534BEF8AAAE740FA021B3C149DDD20A9.PNG",
      "trophyGroupId": "default"
    },
    {
      "trophyId": 50,
      "trophyHidden": false,
      "trophyType": "bronze",
      "trophyName": "Reach 2.500 points in total",
      "trophyDetail": "Reach 2.500 points in total.",
      "trophyIconUrl": "https://image.api.playstation.com/trophy/np/NPWR52904_00_0073B51C08673F152F6BA19616EFA16E248A990142/22E96C0A005E55FE3E71A7D493F74CFCD975A89B.PNG",
      "trophyGroupId": "default"
    },
    {
      "trophyId": 51,
      "trophyHidden": false,
      "trophyType": "bronze",
      "trophyName": "Reach 2.550 points in total",
      "trophyDetail": "Reach 2.550 points in total.",
      "trophyIconUrl": "https://image.api.playstation.com/trophy/np/NPWR52904_00_0073B51C08673F152F6BA19616EFA16E248A990142/1E69B1ED7DD01E27E18279528B85C35224186FE2.PNG",
      "trophyGroupId": "default"
    },
    {
      "trophyId": 52,
      "trophyHidden": false,
      "trophyType": "bronze",
      "trophyName": "Reach 2.600 points in total",
      "trophyDetail": "Reach 2.600 points in total.",
      "trophyIconUrl": "https://image.api.playstation.com/trophy/np/NPWR52904_00_0073B51C08673F152F6BA19616EFA16E248A990142/8D9A12861D56BCDE1692B26EBDA941769E2AE785.PNG",
      "trophyGroupId": "default"
    },
    {
      "trophyId": 53,
      "trophyHidden": false,
      "trophyType": "bronze",
      "trophyName": "Reach 2.650 points in total",
      "trophyDetail": "Reach 2.650 points in total.",
      "trophyIconUrl": "https://image.api.playstation.com/trophy/np/NPWR52904_00_0073B51C08673F152F6BA19616EFA16E248A990142/1A71870F8E274F4FBC970BD32B86D0195BACE749.PNG",
      "trophyGroupId": "default"
    },
    {
      "trophyId": 54,
      "trophyHidden": false,
      "trophyType": "bronze",
      "trophyName": "Reach 2.700 points in total",
      "trophyDetail": "Reach 2.700 points in total.",
      "trophyIconUrl": "https://image.api.playstation.com/trophy/np/NPWR52904_00_0073B51C08673F152F6BA19616EFA16E248A990142/583A8B73438F4916A43602C71033CA022AB9D4EE.PNG",
      "trophyGroupId": "default"
    },
    {
      "trophyId": 55,
      "trophyHidden": false,
      "trophyType": "bronze",
      "trophyName": "Reach 2.750 points in total",
      "trophyDetail": "Reach 2.750 points in total.",
      "trophyIconUrl": "https://image.api.playstation.com/trophy/np/NPWR52904_00_0073B51C08673F152F6BA19616EFA16E248A990142/1DB4EA07DBD8BF1DEDC3BF444557683B8F92F5BE.PNG",
      "trophyGroupId": "default"
    },
    {
      "trophyId": 56,
      "trophyHidden": false,
      "trophyType": "bronze",
      "trophyName": "Reach 2.800 points in total",
      "trophyDetail": "Reach 2.800 points in total.",
      "trophyIconUrl": "https://image.api.playstation.com/trophy/np/NPWR52904_00_0073B51C08673F152F6BA19616EFA16E248A990142/B42B08DD29CFE46EF5C5CCC0F5FEC9845C2B3183.PNG",
      "trophyGroupId": "default"
    },
    {
      "trophyId": 57,
      "trophyHidden": false,
      "trophyType": "bronze",
      "trophyName": "Reach 2.850 points in total",
      "trophyDetail": "Reach 2.850 points in total.",
      "trophyIconUrl": "https://image.api.playstation.com/trophy/np/NPWR52904_00_0073B51C08673F152F6BA19616EFA16E248A990142/A015E589EA9B688A463EC5456853FB8B252C8D50.PNG",
      "trophyGroupId": "default"
    },
    {
      "trophyId": 58,
      "trophyHidden": false,
      "trophyType": "bronze",
      "trophyName": "Reach 2.900 points in total",
      "trophyDetail": "Reach 2.900 points in total.",
      "trophyIconUrl": "https://image.api.playstation.com/trophy/np/NPWR52904_00_0073B51C08673F152F6BA19616EFA16E248A990142/37918D22A8799FD53896FC49D7A890A56BC45A38.PNG",
      "trophyGroupId": "default"
    },
    {
      "trophyId": 59,
      "trophyHidden": false,
      "trophyType": "bronze",
      "trophyName": "Reach 2.950 points in total",
      "trophyDetail": "Reach 2.950 points in total.",
      "trophyIconUrl": "https://image.api.playstation.com/trophy/np/NPWR52904_00_0073B51C08673F152F6BA19616EFA16E248A990142/DC3C264BD3F58C57E9BEEF18D3AFD5FCAC7C673F.PNG",
      "trophyGroupId": "default"
    },
    {
      "trophyId": 60,
      "trophyHidden": false,
      "trophyType": "bronze",
      "trophyName": "Reach 3.000 points in total",
      "trophyDetail": "Reach 3.000 points in total.",
      "trophyIconUrl": "https://image.api.playstation.com/trophy/np/NPWR52904_00_0073B51C08673F152F6BA19616EFA16E248A990142/75DA34F97FA3D17D93BB66F0D78737F3BAC472D5.PNG",
      "trophyGroupId": "default"
    },
    {
      "trophyId": 61,
      "trophyHidden": false,
      "trophyType": "bronze",
      "trophyName": "Reach 3.050 points in total",
      "trophyDetail": "Reach 3.050 points in total.",
      "trophyIconUrl": "https://image.api.playstation.com/trophy/np/NPWR52904_00_0073B51C08673F152F6BA19616EFA16E248A990142/22ED51AA860F7CDDBD4F000B24C88FD255EAF442.PNG",
      "trophyGroupId": "default"
    },
    {
      "trophyId": 62,
      "trophyHidden": false,
      "trophyType": "bronze",
      "trophyName": "Reach 3.100 points in total",
      "trophyDetail": "Reach 3.100 points in total.",
      "trophyIconUrl": "https://image.api.playstation.com/trophy/np/NPWR52904_00_0073B51C08673F152F6BA19616EFA16E248A990142/C0C558CD5BEC9F322A5338596DD5BB3CA5199490.PNG",
      "trophyGroupId": "default"
    },
    {
      "trophyId": 63,
      "trophyHidden": false,
      "trophyType": "bronze",
      "trophyName": "Reach 3.150 points in total",
      "trophyDetail": "Reach 3.150 points in total.",
      "trophyIconUrl": "https://image.api.playstation.com/trophy/np/NPWR52904_00_0073B51C08673F152F6BA19616EFA16E248A990142/CD9F847A6D9ECC3F08A9FE567C0330771039535A.PNG",
      "trophyGroupId": "default"
    },
    {
      "trophyId": 64,
      "trophyHidden": false,
      "trophyType": "bronze",
      "trophyName": "Reach 3.200 points in total",
      "trophyDetail": "Reach 3.200 points in total.",
      "trophyIconUrl": "https://image.api.playstation.com/trophy/np/NPWR52904_00_0073B51C08673F152F6BA19616EFA16E248A990142/DBD37E9D0055730268E079E4457088C2D59AAF80.PNG",
      "trophyGroupId": "default"
    },
    {
      "trophyId": 65,
      "trophyHidden": false,
      "trophyType": "bronze",
      "trophyName": "Reach 3.250 points in total",
      "trophyDetail": "Reach 3.250 points in total.",
      "trophyIconUrl": "https://image.api.playstation.com/trophy/np/NPWR52904_00_0073B51C08673F152F6BA19616EFA16E248A990142/A56E7DF532A6C16C052E4357538F958FE734F55E.PNG",
      "trophyGroupId": "default"
    },
    {
      "trophyId": 66,
      "trophyHidden": false,
      "trophyType": "bronze",
      "trophyName": "Reach 3.300 points in total",
      "trophyDetail": "Reach 3.300 points in total.",
      "trophyIconUrl": "https://image.api.playstation.com/trophy/np/NPWR52904_00_0073B51C08673F152F6BA19616EFA16E248A990142/8E82AAB2BCF34F5F8C1436E769A71523E4E38602.PNG",
      "trophyGroupId": "default"
    },
    {
      "trophyId": 67,
      "trophyHidden": false,
      "trophyType": "bronze",
      "trophyName": "Reach 3.350 points in total",
      "trophyDetail": "Reach 3.350 points in total.",
      "trophyIconUrl": "https://image.api.playstation.com/trophy/np/NPWR52904_00_0073B51C08673F152F6BA19616EFA16E248A990142/6410C4ECC65339D96A2E18754932770739A1DDAF.PNG",
      "trophyGroupId": "default"
    },
    {
      "trophyId": 68,
      "trophyHidden": false,
      "trophyType": "bronze",
      "trophyName": "Reach 3.400 points in total",
      "trophyDetail": "Reach 3.400 points in total.",
      "trophyIconUrl": "https://image.api.playstation.com/trophy/np/NPWR52904_00_0073B51C08673F152F6BA19616EFA16E248A990142/90C40AF48C6629C5DD91B9415F883D7AB963B86E.PNG",
      "trophyGroupId": "default"
    },
    {
      "trophyId": 69,
      "trophyHidden": false,
      "trophyType": "bronze",
      "trophyName": "Reach 3.450 points in total",
      "trophyDetail": "Reach 3.450 points in total.",
      "trophyIconUrl": "https://image.api.playstation.com/trophy/np/NPWR52904_00_0073B51C08673F152F6BA19616EFA16E248A990142/F8FFF3B0D6DEAAFD92978C124D657F60F1F7FF2A.PNG",
      "trophyGroupId": "default"
    },
    {
      "trophyId": 70,
      "trophyHidden": false,
      "trophyType": "bronze",
      "trophyName": "Reach 3.500 points in total",
      "trophyDetail": "Reach 3.500 points in total.",
      "trophyIconUrl": "https://image.api.playstation.com/trophy/np/NPWR52904_00_0073B51C08673F152F6BA19616EFA16E248A990142/7DD4648E506548E40E8AE2425E6AE7A5A2620835.PNG",
      "trophyGroupId": "default"
    }
  ]
}