{
  "npCommunicationId": "NPWR46567_00",
  "title": "Battlefront Trench Warriors: Ops of Warfare",
  "platform": "PS5",
  "trophySetVersion": "01.00",
  "hasTrophyGroups": false,
  "totalItemCount": 23,
  "trophies": [
    {
      "trophyId": 0,
      "trophyHidden": false,
      "trophyType": "platinum",
      "trophyName": "Trophy Master",
      "trophyDetail": "Earn all trophies. Congratulations on earning every trophy in the game, showcasing your exceptional dedication and skill in \"Battlefront Trench Warriors: Ops of Warfare\"",
      "trophyIconUrl": "https://psnobj.prod.dl.playstation.net/psnobj/NPWR46567_00/32cc1341-afa0-41c2-81c7-acb59c554c92.PNG",
      "trophyGroupId": "default"
    },
    {
      "trophyId": 1,
      "trophyHidden": false,
      "trophyType": "bronze",
      "trophyName": "Training Ground",
      "trophyDetail": "Complete the tutorial. You've mastered the basics and are ready for real battles.",
      "trophyIconUrl": "https://psnobj.prod.dl.playstation.net/psnobj/NPWR46567_00/d0134047-19ed-4ac9-a286-b315e7ba387b.PNG",
      "trophyGroupId": "default"
    },
    {
      "trophyId": 2,
      "trophyHidden": false,
      "trophyType": "bronze",
      "trophyName": "10 Missions Completed",
      "trophyDetail": "Complete 10 missions. You've made your first strides in the campaign successfully.",
      "trophyIconUrl": "https://psnobj.prod.dl.playstation.net/psnobj/NPWR46567_00/094c2a1a-ebb5-4d45-8ff0-a6efaed26a85.PNG",
      "trophyGroupId": "default"
    },
    {
      "trophyId": 3,
      "trophyHidden": false,
      "trophyType": "bronze",
      "trophyName": "Master of Destruction",
      "trophyDetail": "Kill 100 enemies. Your combat skills have made a significant impact on the battlefield.",
      "trophyIconUrl": "https://psnobj.prod.dl.playstation.net/psnobj/NPWR46567_00/407767cf-6ace-4d10-b7f3-a6cd111189df.PNG",
      "trophyGroupId": "default"
    },
    {
      "trophyId": 4,
      "trophyHidden": false,
      "trophyType": "bronze",
      "trophyName": "First Medal",
      "trophyDetail": "Earn your first medal. Your achievements are starting to be recognized.",
      "trophyIconUrl": "https://psnobj.prod.dl.playstation.net/psnobj/NPWR46567_00/f4ccabd2-7dd3-4b92-a04f-901187022f52.PNG",
      "trophyGroupId": "default"
    },
    {
      "trophyId": 5,
      "trophyHidden": false,
      "trophyType": "bronze",
      "trophyName": "Assault Peak",
      "trophyDetail": "Complete mission 5 as an Assault soldier. You’ve successfully tackled one of the key tasks.",
      "trophyIconUrl": "https://psnobj.prod.dl.playstation.net/psnobj/NPWR46567_00/6b68796d-f452-463e-88ad-7152d69536dd.PNG",
      "trophyGroupId": "default"
    },
    {
      "trophyId": 6,
      "trophyHidden": false,
      "trophyType": "bronze",
      "trophyName": "Double Mission 10",
      "trophyDetail": "Complete mission 10 twice. You’ve demonstrated both skill and persistence.",
      "trophyIconUrl": "https://psnobj.prod.dl.playstation.net/psnobj/NPWR46567_00/7add328e-16b0-43b8-a5a3-30cf719f1cc8.PNG",
      "trophyGroupId": "default"
    },
    {
      "trophyId": 7,
      "trophyHidden": false,
      "trophyType": "bronze",
      "trophyName": "UPS Eliminator",
      "trophyDetail": "Eliminate 50 enemies with the UPS. This tool has become a reliable ally in your battles.",
      "trophyIconUrl": "https://psnobj.prod.dl.playstation.net/psnobj/NPWR46567_00/071fdfe6-ce65-4ae6-9780-1a237bca1c54.PNG",
      "trophyGroupId": "default"
    },
    {
      "trophyId": 8,
      "trophyHidden": false,
      "trophyType": "bronze",
      "trophyName": "CSAR Destroyer",
      "trophyDetail": "Eliminate 50 enemies with the CSAR. Your effectiveness on the battlefield has been greatly enhanced.",
      "trophyIconUrl": "https://psnobj.prod.dl.playstation.net/psnobj/NPWR46567_00/d2296429-9226-456a-a17e-f40c6a6a058a.PNG",
      "trophyGroupId": "default"
    },
    {
      "trophyId": 9,
      "trophyHidden": false,
      "trophyType": "silver",
      "trophyName": "20 Missions Completed",
      "trophyDetail": "Complete 20 missions. Your exceptional skill and dedication to the cause are evident.",
      "trophyIconUrl": "https://psnobj.prod.dl.playstation.net/psnobj/NPWR46567_00/f7fff213-1499-4d42-83ae-8f6f25233da3.PNG",
      "trophyGroupId": "default"
    },
    {
      "trophyId": 10,
      "trophyHidden": false,
      "trophyType": "silver",
      "trophyName": "Master of Combat",
      "trophyDetail": "Kill 250 enemies. Your combat prowess has been further honed through numerous battles.",
      "trophyIconUrl": "https://psnobj.prod.dl.playstation.net/psnobj/NPWR46567_00/f01fbb82-c2d5-42f6-9cc0-d2c1c93ca138.PNG",
      "trophyGroupId": "default"
    },
    {
      "trophyId": 11,
      "trophyHidden": false,
      "trophyType": "silver",
      "trophyName": "Five Medals",
      "trophyDetail": "Earn 5 medals. Your efforts and achievements are being duly recognized.",
      "trophyIconUrl": "https://psnobj.prod.dl.playstation.net/psnobj/NPWR46567_00/094f7ae1-4425-4604-a4d1-ad040cd72639.PNG",
      "trophyGroupId": "default"
    },
    {
      "trophyId": 12,
      "trophyHidden": false,
      "trophyType": "silver",
      "trophyName": "10 Medals",
      "trophyDetail": "Earn 10 medals. Your successes in combat continue to be rewarded.",
      "trophyIconUrl": "https://psnobj.prod.dl.playstation.net/psnobj/NPWR46567_00/a4acc740-6869-45b6-8768-6ab7d2eb1361.PNG",
      "trophyGroupId": "default"
    },
    {
      "trophyId": 13,
      "trophyHidden": false,
      "trophyType": "silver",
      "trophyName": "Sniper Victory",
      "trophyDetail": "Complete mission 15 as a Scout soldier. Your marksmanship skills have become a decisive factor.",
      "trophyIconUrl": "https://psnobj.prod.dl.playstation.net/psnobj/NPWR46567_00/db8bd2dd-fc4a-430e-9c12-94b42ec9a99b.PNG",
      "trophyGroupId": "default"
    },
    {
      "trophyId": 14,
      "trophyHidden": false,
      "trophyType": "silver",
      "trophyName": "KH415 Eliminator",
      "trophyDetail": "Eliminate 100 enemies with the KH415. This weapon has become your dependable companion in battle.",
      "trophyIconUrl": "https://psnobj.prod.dl.playstation.net/psnobj/NPWR46567_00/73c77858-72f9-4d65-ad6d-938f4c4c1b0f.PNG",
      "trophyGroupId": "default"
    },
    {
      "trophyId": 15,
      "trophyHidden": false,
      "trophyType": "silver",
      "trophyName": "MPM Master",
      "trophyDetail": "Eliminate 100 enemies with the MPM. Your combat skills with this weapon have reached new heights.",
      "trophyIconUrl": "https://psnobj.prod.dl.playstation.net/psnobj/NPWR46567_00/e720bdb7-236d-4f5c-8f34-9b2d359603bc.PNG",
      "trophyGroupId": "default"
    },
    {
      "trophyId": 16,
      "trophyHidden": false,
      "trophyType": "gold",
      "trophyName": "30 Missions Completed",
      "trophyDetail": "Complete 30 missions. Your achievements in the campaign have set you apart as one of the top fighters.",
      "trophyIconUrl": "https://psnobj.prod.dl.playstation.net/psnobj/NPWR46567_00/74a6fb8a-ba5a-4a44-9128-a3279635f9b3.PNG",
      "trophyGroupId": "default"
    },
    {
      "trophyId": 17,
      "trophyHidden": false,
      "trophyType": "gold",
      "trophyName": "500 Kills",
      "trophyDetail": "Kill 500 enemies. Your combat record continues to grow, solidifying your reputation.",
      "trophyIconUrl": "https://psnobj.prod.dl.playstation.net/psnobj/NPWR46567_00/9083038b-675b-4b5d-98a9-358794d028bb.PNG",
      "trophyGroupId": "default"
    },
    {
      "trophyId": 18,
      "trophyHidden": false,
      "trophyType": "gold",
      "trophyName": "15 Medals",
      "trophyDetail": "Earn 15 medals. Your combat achievements have been recognized and rewarded.",
      "trophyIconUrl": "https://psnobj.prod.dl.playstation.net/psnobj/NPWR46567_00/79678ab3-12aa-4382-accc-5d4207f2a82c.PNG",
      "trophyGroupId": "default"
    },
    {
      "trophyId": 19,
      "trophyHidden": false,
      "trophyType": "gold",
      "trophyName": "1000 Kills",
      "trophyDetail": "Kill 1000 enemies. You’ve reached an outstanding level of skill and endurance.",
      "trophyIconUrl": "https://psnobj.prod.dl.playstation.net/psnobj/NPWR46567_00/a2275580-744a-43d4-8424-7f43d06d66d5.PNG",
      "trophyGroupId": "default"
    },
    {
      "trophyId": 20,
      "trophyHidden": false,
      "trophyType": "gold",
      "trophyName": "Infiltrator Peak",
      "trophyDetail": "Complete mission 25 as an Infiltrator soldier. You’ve demonstrated mastery and cunning in challenging conditions.",
      "trophyIconUrl": "https://psnobj.prod.dl.playstation.net/psnobj/NPWR46567_00/6d1a5c71-5206-4119-baf2-8a611cdf122b.PNG",
      "trophyGroupId": "default"
    },
    {
      "trophyId": 21,
      "trophyHidden": false,
      "trophyType": "gold",
      "trophyName": "M19A2 Eliminator",
      "trophyDetail": "Eliminate 150 enemies with the M19A2. This weapon has become a key asset on the battlefield.",
      "trophyIconUrl": "https://psnobj.prod.dl.playstation.net/psnobj/NPWR46567_00/d1b427e5-295d-44f5-a13e-f2fe98428826.PNG",
      "trophyGroupId": "default"
    },
    {
      "trophyId": 22,
      "trophyHidden": false,
      "trophyType": "gold",
      "trophyName": "VSSV Master",
      "trophyDetail": "Eliminate 150 enemies with the VSSV. Your proficiency with this weapon has reached the highest level.",
      "trophyIconUrl": "https://psnobj.prod.dl.playstation.net/psnobj/NPWR46567_00/3d8efd28-1a8f-4d2e-a093-01b7a5aca929.PNG",
      "trophyGroupId": "default"
    }
  ]
}